{
    "display": {
        "title": {
            "text": "Phantom"
        },
        "description": {
            "text": "Defeat at least one Phantom."
        },
        "icon": {
            "item": "minecraft:phantom_spawn_egg"
        },
        "frame": "task",
        "show_toast": true,
        "announce_to_chat": true,
        "hidden": false
    },
    "criteria": {
        "Claim": {
            "trigger": "minecraft:player_killed_entity",
            "conditions": {
                "entity": {
                    "type": "minecraft:phantom"
                }
            }
        }
    },
    "rewards": {
        "loot": [
            "neomanila:reward1_common"
        ]
    },
    "parent": "neomanila:exterminate/hostile/guardian"
}