{
    "display": {
        "title": {
            "text": "Deer"
        },
        "description": {
            "text": "Defeat at least one Deer."
        },
        "icon": {
            "item": "adventurez:spawn_deer"
        },
        "frame": "task",
        "show_toast": true,
        "announce_to_chat": true,
        "hidden": false
    },
    "criteria": {
        "Claim": {
            "trigger": "minecraft:player_killed_entity",
            "conditions": {
                "entity": {
                    "type": "adventurez:deer"
                }
            }
        }
    },
    "rewards": {
        "loot": [
            "neomanila:reward1_common"
        ]
    },
    "parent": "neomanila:exterminate/passive_land/strider"
}